simulations/spi/spi_working_verified.sv
`timescale 1ns/1ps

// SPI MASTER - Mode 0 (CPOL=0, CPHA=0)
// Clock idles low, sample on rising edge, change on falling edge
module spi_master #(parameter WIDTH=8) (
    input  wire clk, rst_n,
    input  wire [WIDTH-1:0] tx_data,
    input  wire start,
    output reg  [WIDTH-1:0] rx_data,
    output reg  done,
    output reg  sclk, mosi, cs_n,
    input  wire miso
);
    reg [WIDTH-1:0] tx_reg, rx_reg;
    reg [3:0] bit_cnt;
    reg [2:0] clk_cnt;
    reg [1:0] state;
    
    localparam IDLE=0, XFER=1, FINISH=2;
    
    always @(posedge clk or negedge rst_n) begin
        if (!rst_n) begin
            state <= IDLE;
            done <= 0;
            sclk <= 0;
            cs_n <= 1;
        end else begin
            done <= 0;
            case (state)
                IDLE: if (start) begin
                    tx_reg <= tx_data;
                    bit_cnt <= 0;
                    clk_cnt <= 0;
                    cs_n <= 0;
                    sclk <= 0;
                    state <= XFER;
                end
                
                XFER: begin
                    clk_cnt <= clk_cnt + 1;
                    if (clk_cnt == 3) begin
                        clk_cnt <= 0;
                        sclk <= ~sclk;
                        if (!sclk) begin  // About to rise
                            // Sample will happen
                        end else begin  // About to fall
                            rx_reg <= {rx_reg[WIDTH-2:0], miso};
                            tx_reg <= {tx_reg[WIDTH-2:0], 1'b0};
                            bit_cnt <= bit_cnt + 1;
                            if (bit_cnt == WIDTH-1)
                                state <= FINISH;
                        end
                    end
                end
                
                FINISH: begin
                    rx_data <= rx_reg;
                    done <= 1;
                    cs_n <= 1;
                    sclk <= 0;
                    state <= IDLE;
                end
            endcase
        end
    end
    assign mosi = tx_reg[WIDTH-1];
endmodule

// SPI SLAVE
module spi_slave #(parameter WIDTH=8) (
    input  wire clk, rst_n,
    input  wire [WIDTH-1:0] tx_data,
    output reg  [WIDTH-1:0] rx_data,
    output reg  done,
    input  wire sclk, mosi, cs_n,
    output wire miso
);
    reg [WIDTH-1:0] tx_reg, rx_reg;
    reg [3:0] bit_cnt;
    reg sclk_d, cs_d;
    
    always @(posedge clk or negedge rst_n) begin
        if (!rst_n) begin
            sclk_d <= 0;
            cs_d <= 1;
            done <= 0;
        end else begin
            sclk_d <= sclk;
            cs_d <= cs_n;
            done <= 0;
            
            if (cs_d && !cs_n) begin  // CS falling
                tx_reg <= tx_data;
                bit_cnt <= 0;
            end else if (!cs_n && !sclk_d && sclk) begin  // SCLK rising during transfer
                rx_reg <= {rx_reg[WIDTH-2:0], mosi};
                bit_cnt <= bit_cnt + 1;
            end else if (!cs_n && sclk_d && !sclk) begin  // SCLK falling during transfer
                tx_reg <= {tx_reg[WIDTH-2:0], 1'b0};
            end else if (!cs_d && cs_n && bit_cnt == WIDTH) begin  // CS rising after transfer
                rx_data <= rx_reg;
                done <= 1;
            end
        end
    end
    assign miso = cs_n ? 1'bz : tx_reg[WIDTH-1];
endmodule

// TESTBENCH
module tb;
    reg clk=0, rst_n;
    reg [7:0] m_tx, s_tx;
    wire [7:0] m_rx, s_rx;
    reg start;
    wire m_done, s_done;
    wire sclk, mosi, miso, cs_n;
    
    always #5 clk = ~clk;
    
    spi_master m(.clk(clk), .rst_n(rst_n), .tx_data(m_tx), .start(start),
                 .rx_data(m_rx), .done(m_done),
                 .sclk(sclk), .mosi(mosi), .cs_n(cs_n), .miso(miso));
    
    spi_slave s(.clk(clk), .rst_n(rst_n), .tx_data(s_tx),
                .rx_data(s_rx), .done(s_done),
                .sclk(sclk), .mosi(mosi), .cs_n(cs_n), .miso(miso));
    
    integer pass=0, fail=0;
    
    initial begin
        $dumpfile("spi.vcd");
        $dumpvars;
        
        $display("\n========== SPI SIMULATION ==========\n");
        
        rst_n=0; start=0; #30 rst_n=1; #20;
        
        // Test 1
        m_tx=8'hA5; s_tx=8'h5A; start=1; #10 start=0; #800;
        if (m_rx==8'h5A && s_rx==8'hA5) begin
            $display("✓ Test 1 PASS: M:A5→5A S:5A→A5");
            pass=pass+1;
        end else begin
            $display("✗ Test 1 FAIL: M_RX=%h(exp 5A) S_RX=%h(exp A5)", m_rx, s_rx);
            fail=fail+1;
        end
        
        // Test 2
        m_tx=8'h3C; s_tx=8'hC3; start=1; #10 start=0; #800;
        if (m_rx==8'hC3 && s_rx==8'h3C) begin
            $display("✓ Test 2 PASS: M:3C→C3 S:C3→3C");
            pass=pass+1;
        end else begin
            $display("✗ Test 2 FAIL: M_RX=%h(exp C3) S_RX=%h(exp 3C)", m_rx, s_rx);
            fail=fail+1;
        end
        
        // Test 3
        m_tx=8'hFF; s_tx=8'h00; start=1; #10 start=0; #800;
        if (m_rx==8'h00 && s_rx==8'hFF) begin
            $display("✓ Test 3 PASS: M:FF→00 S:00→FF");
            pass=pass+1;
        end else begin
            $display("✗ Test 3 FAIL: M_RX=%h(exp 00) S_RX=%h(exp FF)", m_rx, s_rx);
            fail=fail+1;
        end
        
        $display("\n====================================");
        $display("PASSED: %0d  FAILED: %0d", pass, fail);
        $display("====================================\n");
        $finish;
    end
endmodule

simulations/spi/spi.vcd
$date
	Tue Nov 18 11:23:52 2025
$end
$version
	Icarus Verilog
$end
$timescale
	1ps
$end
$scope module tb $end
$var wire 1 ! sclk $end
$var wire 8 " s_rx [7:0] $end
$var wire 1 # s_done $end
$var wire 1 $ mosi $end
$var wire 1 % miso $end
$var wire 8 & m_rx [7:0] $end
$var wire 1 ' m_done $end
$var wire 1 ( cs_n $end
$var reg 1 ) clk $end
$var reg 8 * m_tx [7:0] $end
$var reg 1 + rst_n $end
$var reg 8 , s_tx [7:0] $end
$var reg 1 - start $end
$var integer 32 . fail [31:0] $end
$var integer 32 / pass [31:0] $end
$scope module m $end
$var wire 1 ) clk $end
$var wire 1 + rst_n $end
$var wire 1 - start $end
$var wire 8 0 tx_data [7:0] $end
$var wire 1 $ mosi $end
$var wire 1 % miso $end
$var parameter 32 1 FINISH $end
$var parameter 32 2 IDLE $end
$var parameter 32 3 WIDTH $end
$var parameter 32 4 XFER $end
$var reg 4 5 bit_cnt [3:0] $end
$var reg 3 6 clk_cnt [2:0] $end
$var reg 1 ( cs_n $end
$var reg 1 ' done $end
$var reg 8 7 rx_data [7:0] $end
$var reg 8 8 rx_reg [7:0] $end
$var reg 1 ! sclk $end
$var reg 2 9 state [1:0] $end
$var reg 8 : tx_reg [7:0] $end
$upscope $end
$scope module s $end
$var wire 1 ) clk $end
$var wire 1 ( cs_n $end
$var wire 1 $ mosi $end
$var wire 1 + rst_n $end
$var wire 1 ! sclk $end
$var wire 8 ; tx_data [7:0] $end
$var wire 1 % miso $end
$var parameter 32 < WIDTH $end
$var reg 4 = bit_cnt [3:0] $end
$var reg 1 > cs_d $end
$var reg 1 # done $end
$var reg 8 ? rx_data [7:0] $end
$var reg 8 @ rx_reg [7:0] $end
$var reg 1 A sclk_d $end
$var reg 8 B tx_reg [7:0] $end
$upscope $end
$upscope $end
$enddefinitions $end
$comment Show the parameter values. $end
$dumpall
b1000 <
b1 4
b1000 3
b0 2
b10 1
$end
#0
$dumpvars
bx B
0A
bx @
bx ?
1>
bx =
bx ;
bx :
b0 9
bx 8
bx 7
bx 6
bx 5
bx 0
b0 /
b0 .
0-
bx ,
0+
bx *
0)
1(
0'
bx &
z%
x$
0#
bx "
0!
$end
#5000
1)
#10000
0)
#15000
1)
#20000
0)
#25000
1)
#30000
0)
1+
#35000
1)
#40000
0)
#45000
1)
#50000
0)
1-
b1011010 ,
b1011010 ;
b10100101 *
b10100101 0
#55000
x%
1$
b1 9
0(
b0 6
b0 5
b10100101 :
1)
#60000
0)
0-
#65000
0%
b0 =
b1011010 B
0>
b1 6
1)
#70000
0)
#75000
b10 6
1)
#80000
0)
#85000
b11 6
1)
#90000
0)
#95000
1!
b0 6
1)
#100000
0)
#105000
b1 =
bx1 @
1A
b1 6
1)
#110000
0)
#115000
b10 6
1)
#120000
0)
#125000
b11 6
1)
#130000
0)
#135000
0$
b1 5
b1001010 :
bx0 8
0!
b0 6
1)
#140000
0)
#145000
1%
b10110100 B
0A
b1 6
1)
#150000
0)
#155000
b10 6
1)
#160000
0)
#165000
b11 6
1)
#170000
0)
#175000
1!
b0 6
1)
#180000
0)
#185000
b10 =
bx10 @
1A
b1 6
1)
#190000
0)
#195000
b10 6
1)
#200000
0)
#205000
b11 6
1)
#210000
0)
#215000
1$
b10 5
b10010100 :
bx01 8
0!
b0 6
1)
#220000
0)
#225000
0%
b1101000 B
0A
b1 6
1)
#230000
0)
#235000
b10 6
1)
#240000
0)
#245000
b11 6
1)
#250000
0)
#255000
1!
b0 6
1)
#260000
0)
#265000
b11 =
bx101 @
1A
b1 6
1)
#270000
0)
#275000
b10 6
1)
#280000
0)
#285000
b11 6
1)
#290000
0)
#295000
0$
b11 5
b101000 :
bx010 8
0!
b0 6
1)
#300000
0)
#305000
1%
b11010000 B
0A
b1 6
1)
#310000
0)
#315000
b10 6
1)
#320000
0)
#325000
b11 6
1)
#330000
0)
#335000
1!
b0 6
1)
#340000
0)
#345000
b100 =
bx1010 @
1A
b1 6
1)
#350000
0)
#355000
b10 6
1)
#360000
0)
#365000
b11 6
1)
#370000
0)
#375000
b100 5
b1010000 :
bx0101 8
0!
b0 6
1)
#380000
0)
#385000
b10100000 B
0A
b1 6
1)
#390000
0)
#395000
b10 6
1)
#400000
0)
#405000
b11 6
1)
#410000
0)
#415000
1!
b0 6
1)
#420000
0)
#425000
b101 =
bx10100 @
1A
b1 6
1)
#430000
0)
#435000
b10 6
1)
#440000
0)
#445000
b11 6
1)
#450000
0)
#455000
1$
b101 5
b10100000 :
bx01011 8
0!
b0 6
1)
#460000
0)
#465000
0%
b1000000 B
0A
b1 6
1)
#470000
0)
#475000
b10 6
1)
#480000
0)
#485000
b11 6
1)
#490000
0)
#495000
1!
b0 6
1)
#500000
0)
#505000
b110 =
bx101001 @
1A
b1 6
1)
#510000
0)
#515000
b10 6
1)
#520000
0)
#525000
b11 6
1)
#530000
0)
#535000
0$
b110 5
b1000000 :
bx010110 8
0!
b0 6
1)
#540000
0)
#545000
1%
b10000000 B
0A
b1 6
1)
#550000
0)
#555000
b10 6
1)
#560000
0)
#565000
b11 6
1)
#570000
0)
#575000
1!
b0 6
1)
#580000
0)
#585000
b111 =
bx1010010 @
1A
b1 6
1)
#590000
0)
#595000
b10 6
1)
#600000
0)
#605000
b11 6
1)
#610000
0)
#615000
1$
b111 5
b10000000 :
bx0101101 8
0!
b0 6
1)
#620000
0)
#625000
0%
b0 B
0A
b1 6
1)
#630000
0)
#635000
b10 6
1)
#640000
0)
#645000
b11 6
1)
#650000
0)
#655000
1!
b0 6
1)
#660000
0)
#665000
b1000 =
b10100101 @
1A
b1 6
1)
#670000
0)
#675000
b10 6
1)
#680000
0)
#685000
b11 6
1)
#690000
0)
#695000
0$
b10 9
b1000 5
b0 :
b1011010 8
0!
b0 6
1)
#700000
0)
#705000
z%
0A
b0 9
1(
1'
b1011010 &
b1011010 7
1)
#710000
0)
#715000
0'
1#
b10100101 "
b10100101 ?
1>
1)
#720000
0)
#725000
0#
1)
#730000
0)
#735000
1)
#740000
0)
#745000
1)
#750000
0)
#755000
1)
#760000
0)
#765000
1)
#770000
0)
#775000
1)
#780000
0)
#785000
1)
#790000
0)
#795000
1)
#800000
0)
#805000
1)
#810000
0)
#815000
1)
#820000
0)
#825000
1)
#830000
0)
#835000
1)
#840000
0)
#845000
1)
#850000
0)
#855000
1)
#860000
0)
1-
b11000011 ,
b11000011 ;
b111100 *
b111100 0
b1 /
#865000
0%
b1 9
0(
b0 5
b111100 :
1)
#870000
0)
0-
#875000
1%
b1 6
b0 =
b11000011 B
0>
1)
#880000
0)
#885000
b10 6
1)
#890000
0)
#895000
b11 6
1)
#900000
0)
#905000
1!
b0 6
1)
#910000
0)
#915000
b1 6
b1 =
b1001010 @
1A
1)
#920000
0)
#925000
b10 6
1)
#930000
0)
#935000
b11 6
1)
#940000
0)
#945000
b1 5
b1111000 :
b10110101 8
0!
b0 6
1)
#950000
0)
#955000
b1 6
b10000110 B
0A
1)
#960000
0)
#965000
b10 6
1)
#970000
0)
#975000
b11 6
1)
#980000
0)
#985000
1!
b0 6
1)
#990000
0)
#995000
b1 6
b10 =
b10010100 @
1A
1)
#1000000
0)
#1005000
b10 6
1)
#1010000
0)
#1015000
b11 6
1)
#1020000
0)
#1025000
1$
b10 5
b11110000 :
b1101011 8
0!
b0 6
1)
#1030000
0)
#1035000
0%
b1 6
b1100 B
0A
1)
#1040000
0)
#1045000
b10 6
1)
#1050000
0)
#1055000
b11 6
1)
#1060000
0)
#1065000
1!
b0 6
1)
#1070000
0)
#1075000
b1 6
b11 =
b101001 @
1A
1)
#1080000
0)
#1085000
b10 6
1)
#1090000
0)
#1095000
b11 6
1)
#1100000
0)
#1105000
b11 5
b11100000 :
b11010110 8
0!
b0 6
1)
#1110000
0)
#1115000
b1 6
b11000 B
0A
1)
#1120000
0)
#1125000
b10 6
1)
#1130000
0)
#1135000
b11 6
1)
#1140000
0)
#1145000
1!
b0 6
1)
#1150000
0)
#1155000
b1 6
b100 =
b1010011 @
1A
1)
#1160000
0)
#1165000
b10 6
1)
#1170000
0)
#1175000
b11 6
1)
#1180000
0)
#1185000
b100 5
b11000000 :
b10101100 8
0!
b0 6
1)
#1190000
0)
#1195000
b1 6
b110000 B
0A
1)
#1200000
0)
#1205000
b10 6
1)
#1210000
0)
#1215000
b11 6
1)
#1220000
0)
#1225000
1!
b0 6
1)
#1230000
0)
#1235000
b1 6
b101 =
b10100111 @
1A
1)
#1240000
0)
#1245000
b10 6
1)
#1250000
0)
#1255000
b11 6
1)
#1260000
0)
#1265000
b101 5
b10000000 :
b1011000 8
0!
b0 6
1)
#1270000
0)
#1275000
b1 6
b1100000 B
0A
1)
#1280000
0)
#1285000
b10 6
1)
#1290000
0)
#1295000
b11 6
1)
#1300000
0)
#1305000
1!
b0 6
1)
#1310000
0)
#1315000
b1 6
b110 =
b1001111 @
1A
1)
#1320000
0)
#1325000
b10 6
1)
#1330000
0)
#1335000
b11 6
1)
#1340000
0)
#1345000
0$
b110 5
b0 :
b10110000 8
0!
b0 6
1)
#1350000
0)
#1355000
1%
b1 6
b11000000 B
0A
1)
#1360000
0)
#1365000
b10 6
1)
#1370000
0)
#1375000
b11 6
1)
#1380000
0)
#1385000
1!
b0 6
1)
#1390000
0)
#1395000
b1 6
b111 =
b10011110 @
1A
1)
#1400000
0)
#1405000
b10 6
1)
#1410000
0)
#1415000
b11 6
1)
#1420000
0)
#1425000
b111 5
b1100001 8
0!
b0 6
1)
#1430000
0)
#1435000
b1 6
b10000000 B
0A
1)
#1440000
0)
#1445000
b10 6
1)
#1450000
0)
#1455000
b11 6
1)
#1460000
0)
#1465000
1!
b0 6
1)
#1470000
0)
#1475000
b1 6
b1000 =
b111100 @
1A
1)
#1480000
0)
#1485000
b10 6
1)
#1490000
0)
#1495000
b11 6
1)
#1500000
0)
#1505000
b10 9
b1000 5
b11000011 8
0!
b0 6
1)
#1510000
0)
#1515000
z%
b0 9
1(
1'
b11000011 &
b11000011 7
b0 B
0A
1)
#1520000
0)
#1525000
1#
b111100 "
b111100 ?
1>
0'
1)
#1530000
0)
#1535000
0#
1)
#1540000
0)
#1545000
1)
#1550000
0)
#1555000
1)
#1560000
0)
#1565000
1)
#1570000
0)
#1575000
1)
#1580000
0)
#1585000
1)
#1590000
0)
#1595000
1)
#1600000
0)
#1605000
1)
#1610000
0)
#1615000
1)
#1620000
0)
#1625000
1)
#1630000
0)
#1635000
1)
#1640000
0)
#1645000
1)
#1650000
0)
#1655000
1)
#1660000
0)
#1665000
1)
#1670000
0)
1-
b0 ,
b0 ;
b11111111 *
b11111111 0
b10 /
#1675000
0%
1$
b1 9
0(
b0 5
b11111111 :
1)
#1680000
0)
0-
#1685000
b0 =
0>
b1 6
1)
#1690000
0)
#1695000
b10 6
1)
#1700000
0)
#1705000
b11 6
1)
#1710000
0)
#1715000
1!
b0 6
1)
#1720000
0)
#1725000
b1 =
b1111001 @
1A
b1 6
1)
#1730000
0)
#1735000
b10 6
1)
#1740000
0)
#1745000
b11 6
1)
#1750000
0)
#1755000
b1 5
b11111110 :
b10000110 8
0!
b0 6
1)
#1760000
0)
#1765000
0A
b1 6
1)
#1770000
0)
#1775000
b10 6
1)
#1780000
0)
#1785000
b11 6
1)
#1790000
0)
#1795000
1!
b0 6
1)
#1800000
0)
#1805000
b10 =
b11110011 @
1A
b1 6
1)
#1810000
0)
#1815000
b10 6
1)
#1820000
0)
#1825000
b11 6
1)
#1830000
0)
#1835000
b10 5
b11111100 :
b1100 8
0!
b0 6
1)
#1840000
0)
#1845000
0A
b1 6
1)
#1850000
0)
#1855000
b10 6
1)
#1860000
0)
#1865000
b11 6
1)
#1870000
0)
#1875000
1!
b0 6
1)
#1880000
0)
#1885000
b11 =
b11100111 @
1A
b1 6
1)
#1890000
0)
#1895000
b10 6
1)
#1900000
0)
#1905000
b11 6
1)
#1910000
0)
#1915000
b11 5
b11111000 :
b11000 8
0!
b0 6
1)
#1920000
0)
#1925000
0A
b1 6
1)
#1930000
0)
#1935000
b10 6
1)
#1940000
0)
#1945000
b11 6
1)
#1950000
0)
#1955000
1!
b0 6
1)
#1960000
0)
#1965000
b100 =
b11001111 @
1A
b1 6
1)
#1970000
0)
#1975000
b10 6
1)
#1980000
0)
#1985000
b11 6
1)
#1990000
0)
#1995000
b100 5
b11110000 :
b110000 8
0!
b0 6
1)
#2000000
0)
#2005000
0A
b1 6
1)
#2010000
0)
#2015000
b10 6
1)
#2020000
0)
#2025000
b11 6
1)
#2030000
0)
#2035000
1!
b0 6
1)
#2040000
0)
#2045000
b101 =
b10011111 @
1A
b1 6
1)
#2050000
0)
#2055000
b10 6
1)
#2060000
0)
#2065000
b11 6
1)
#2070000
0)
#2075000
b101 5
b11100000 :
b1100000 8
0!
b0 6
1)
#2080000
0)
#2085000
0A
b1 6
1)
#2090000
0)
#2095000
b10 6
1)
#2100000
0)
#2105000
b11 6
1)
#2110000
0)
#2115000
1!
b0 6
1)
#2120000
0)
#2125000
b110 =
b111111 @
1A
b1 6
1)
#2130000
0)
#2135000
b10 6
1)
#2140000
0)
#2145000
b11 6
1)
#2150000
0)
#2155000
b110 5
b11000000 :
b11000000 8
0!
b0 6
1)
#2160000
0)
#2165000
0A
b1 6
1)
#2170000
0)
#2175000
b10 6
1)
#2180000
0)
#2185000
b11 6
1)
#2190000
0)
#2195000
1!
b0 6
1)
#2200000
0)
#2205000
b111 =
b1111111 @
1A
b1 6
1)
#2210000
0)
#2215000
b10 6
1)
#2220000
0)
#2225000
b11 6
1)
#2230000
0)
#2235000
b111 5
b10000000 :
b10000000 8
0!
b0 6
1)
#2240000
0)
#2245000
0A
b1 6
1)
#2250000
0)
#2255000
b10 6
1)
#2260000
0)
#2265000
b11 6
1)
#2270000
0)
#2275000
1!
b0 6
1)
#2280000
0)
#2285000
b1000 =
b11111111 @
1A
b1 6
1)
#2290000
0)
#2295000
b10 6
1)
#2300000
0)
#2305000
b11 6
1)
#2310000
0)
#2315000
0$
b10 9
b1000 5
b0 :
b0 8
0!
b0 6
1)
#2320000
0)
#2325000
z%
0A
b0 9
1(
1'
b0 &
b0 7
1)
#2330000
0)
#2335000
0'
1#
b11111111 "
b11111111 ?
1>
1)
#2340000
0)
#2345000
0#
1)
#2350000
0)
#2355000
1)
#2360000
0)
#2365000
1)
#2370000
0)
#2375000
1)
#2380000
0)
#2385000
1)
#2390000
0)
#2395000
1)
#2400000
0)
#2405000
1)
#2410000
0)
#2415000
1)
#2420000
0)
#2425000
1)
#2430000
0)
#2435000
1)
#2440000
0)
#2445000
1)
#2450000
0)
#2455000
1)
#2460000
0)
#2465000
1)
#2470000
0)
#2475000
1)
#2480000
0)
b11 /
